{
  "platform": "youtube",
  "mode": "general",
  "regions": {
    "KR_trending": [
      {
        "rank": 1,
        "title": "BTS (방탄소년단) ‘NORMAL’ Official MV",
        "video_id": "GEk4jHwfFTA",
        "url": "https://www.youtube.com/watch?v=GEk4jHwfFTA",
        "channel": "HYBE LABELS",
        "views": 5550902,
        "likes": 968990,
        "comments": 50193,
        "published": "2026-07-19T04:00:02Z",
        "category": "10"
      },
      {
        "rank": 2,
        "title": "[암살자(들)] 티저 예고편",
        "video_id": "XH5EgzoMs-s",
        "url": "https://www.youtube.com/watch?v=XH5EgzoMs-s",
        "channel": "hivemedia_corp",
        "views": 689185,
        "likes": 949,
        "comments": 309,
        "published": "2026-07-19T23:02:34Z",
        "category": "1"
      },
      {
        "rank": 3,
        "title": "유골함 압수",
        "video_id": "OfJ3MdPPRT0",
        "url": "https://www.youtube.com/watch?v=OfJ3MdPPRT0",
        "channel": "랄로",
        "views": 675875,
        "likes": 4687,
        "comments": 569,
        "published": "2026-07-19T07:20:36Z",
        "category": "20"
      },
      {
        "rank": 4,
        "title": "Brainwash",
        "video_id": "VNLUaTxDs_4",
        "url": "https://www.youtube.com/watch?v=VNLUaTxDs_4",
        "channel": "HEEDAE - Topic",
        "views": 240638,
        "likes": 3247,
        "comments": 0,
        "published": "2026-07-18T09:03:58Z",
        "category": "10"
      },
      {
        "rank": 5,
        "title": "[ 김부장 9화 예고]토사구팽당한 김부장과 리응령의 최후! 김부장에게 총구겨눈 주강찬을 들이받을 최종 조력자의 정체#최대훈 #윤경호 #SBS금토드라마",
        "video_id": "OaBBO6e51tE",
        "url": "https://www.youtube.com/watch?v=OaBBO6e51tE",
        "channel": "Dramatic Drama",
        "views": 154730,
        "likes": 1249,
        "comments": 100,
        "published": "2026-07-18T19:15:38Z",
        "category": "1"
      },
      {
        "rank": 6,
        "title": "[ 불도그 LIVE 생방송 7/19 ] 리니지 클래식 오랜만이에요. 중대발표 저도 하겠습니다.",
        "video_id": "heAaqSlq26w",
        "url": "https://www.youtube.com/watch?v=heAaqSlq26w",
        "channel": "불도그",
        "views": 284424,
        "likes": 2296,
        "comments": 203,
        "published": "2026-07-19T19:15:27Z",
        "category": "20"
      },
      {
        "rank": 7,
        "title": "[Live Clip] V.O.Sㅣ사고쳤어요(2026) (I made a mistake)ㅣ4K",
        "video_id": "_KUgWZQEinE",
        "url": "https://www.youtube.com/watch?v=_KUgWZQEinE",
        "channel": "1theK (원더케이)",
        "views": 85274,
        "likes": 2302,
        "comments": 374,
        "published": "2026-07-19T09:00:09Z",
        "category": "10"
      },
      {
        "rank": 8,
        "title": "《암살자들》 첫 예고편 떴다..!!🔥 \"내부자들, 남산의 부장들, 서울의 봄\" 다음 현대사 유니버스 영화 ㄷㄷ 1974년 영부인 저격 사건 최초 영화화..",
        "video_id": "OVoHvRhiLnY",
        "url": "https://www.youtube.com/watch?v=OVoHvRhiLnY",
        "channel": "엘플릭스 [LPLIX]",
        "views": 29850,
        "likes": 453,
        "comments": 87,
        "published": "2026-07-20T04:00:35Z",
        "category": "1"
      },
      {
        "rank": 9,
        "title": "🤣혜안져스 노움강도단 대환장 합방ㅋㅋㅋㅋㅋㅋㅋㅋ🤣",
        "video_id": "rQsiS_1cYTs",
        "url": "https://www.youtube.com/watch?v=rQsiS_1cYTs",
        "channel": "혜안",
        "views": 434563,
        "likes": 14849,
        "comments": 1499,
        "published": "2026-07-19T10:13:36Z",
        "category": "20"
      },
      {
        "rank": 10,
        "title": "I made a mistake",
        "video_id": "sEA5NGU7KW4",
        "url": "https://www.youtube.com/watch?v=sEA5NGU7KW4",
        "channel": "V.O.S - Topic",
        "views": 51600,
        "likes": 1864,
        "comments": 0,
        "published": "2026-07-19T09:00:03Z",
        "category": "10"
      },
      {
        "rank": 11,
        "title": "가난한데 예쁜 할머니가 할아버지한테 한 충격적인 짓... 미친 소재로 전세계를 놀라게 한 명작 한국 영화",
        "video_id": "gsfLwobl-mM",
        "url": "https://www.youtube.com/watch?v=gsfLwobl-mM",
        "channel": "리씨네",
        "views": 34674,
        "likes": 346,
        "comments": 15,
        "published": "2026-07-18T09:00:38Z",
        "category": "1"
      },
      {
        "rank": 12,
        "title": "괴물",
        "video_id": "yLGVA_B6jYk",
        "url": "https://www.youtube.com/watch?v=yLGVA_B6jYk",
        "channel": "PAKA",
        "views": 181038,
        "likes": 1463,
        "comments": 332,
        "published": "2026-07-20T08:30:13Z",
        "category": "20"
      },
      {
        "rank": 13,
        "title": "Don't Be Happy",
        "video_id": "jgjd9Ph0VhM",
        "url": "https://www.youtube.com/watch?v=jgjd9Ph0VhM",
        "channel": "DK - Topic",
        "views": 41473,
        "likes": 501,
        "comments": 32,
        "published": "2026-07-19T09:04:17Z",
        "category": "10"
      },
      {
        "rank": 14,
        "title": "[경주기행] 티저 예고편🚌",
        "video_id": "YGDI86luY78",
        "url": "https://www.youtube.com/watch?v=YGDI86luY78",
        "channel": "롯데엔터테인먼트",
        "views": 79915,
        "likes": 494,
        "comments": 83,
        "published": "2026-07-19T22:30:21Z",
        "category": "1"
      },
      {
        "rank": 15,
        "title": "돌아온 하이퍼캐리 원딜",
        "video_id": "7H_L97sca6w",
        "url": "https://www.youtube.com/watch?v=7H_L97sca6w",
        "channel": "괴물쥐 유튜브",
        "views": 350245,
        "likes": 1799,
        "comments": 215,
        "published": "2026-07-19T13:00:37Z",
        "category": "20"
      }
    ],
    "US_trending": [
      {
        "rank": 1,
        "title": "BTS (방탄소년단) ‘NORMAL’ Official MV",
        "video_id": "GEk4jHwfFTA",
        "url": "https://www.youtube.com/watch?v=GEk4jHwfFTA",
        "channel": "HYBE LABELS",
        "views": 5550902,
        "likes": 968990,
        "comments": 50193,
        "published": "2026-07-19T04:00:02Z",
        "category": "10"
      },
      {
        "rank": 2,
        "title": "Faces of Grief - Release Date Trailer",
        "video_id": "rEaN_XuLp2I",
        "url": "https://www.youtube.com/watch?v=rEaN_XuLp2I",
        "channel": "The Walten Files",
        "views": 126917,
        "likes": 20307,
        "comments": 1647,
        "published": "2026-07-20T03:30:02Z",
        "category": "22"
      },
      {
        "rank": 3,
        "title": "CDL CHAMPS VEGAS GRAND FINALS!! OpTic TEXAS VS FAZE VEGAS",
        "video_id": "38kUQ70R3H8",
        "url": "https://www.youtube.com/watch?v=38kUQ70R3H8",
        "channel": "Scump",
        "views": 618573,
        "likes": 28123,
        "comments": 377,
        "published": "2026-07-20T01:15:07Z",
        "category": "20"
      },
      {
        "rank": 4,
        "title": "Em i orait - Tonton Malele (feat. Jarahn & Rich Anthony) Official Music Video",
        "video_id": "591W58EnuTQ",
        "url": "https://www.youtube.com/watch?v=591W58EnuTQ",
        "channel": "Tonton Malele",
        "views": 180902,
        "likes": 5632,
        "comments": 315,
        "published": "2026-07-10T09:02:15Z",
        "category": "10"
      },
      {
        "rank": 5,
        "title": "SPIDER-MAN BRAND NEW DAY TRAILER: Power Of The Phoenix Force & Things You Missed!",
        "video_id": "AXy86CAY12A",
        "url": "https://www.youtube.com/watch?v=AXy86CAY12A",
        "channel": "Emergency Awesome",
        "views": 127140,
        "likes": 4201,
        "comments": 537,
        "published": "2026-07-19T23:56:26Z",
        "category": "24"
      },
      {
        "rank": 6,
        "title": "Forest Lookout…",
        "video_id": "gzix2wmXpHM",
        "url": "https://www.youtube.com/watch?v=gzix2wmXpHM",
        "channel": "CaseOh",
        "views": 453372,
        "likes": 19123,
        "comments": 1181,
        "published": "2026-07-19T22:00:13Z",
        "category": "20"
      },
      {
        "rank": 7,
        "title": "Sauce Walka - Brandy Lil Brother (Official Music Video)",
        "video_id": "67o0ubdLAtE",
        "url": "https://www.youtube.com/watch?v=67o0ubdLAtE",
        "channel": "SauceDatTV",
        "views": 203092,
        "likes": 13144,
        "comments": 1663,
        "published": "2026-07-19T05:43:00Z",
        "category": "10"
      },
      {
        "rank": 8,
        "title": "Marvel Hall H SDCC: Doomsday Trailer, X-Men Cast, Or… | Sneak Peek",
        "video_id": "dK-J7dBTyKc",
        "url": "https://www.youtube.com/watch?v=dK-J7dBTyKc",
        "channel": "New Rockstars",
        "views": 119254,
        "likes": 3351,
        "comments": 335,
        "published": "2026-07-19T15:00:24Z",
        "category": "24"
      },
      {
        "rank": 9,
        "title": "I Became THE Chameleon in Meccha Chameleon",
        "video_id": "RXIlbkMEYlo",
        "url": "https://www.youtube.com/watch?v=RXIlbkMEYlo",
        "channel": "SMii7Y",
        "views": 2853729,
        "likes": 144488,
        "comments": 3398,
        "published": "2026-07-18T19:13:27Z",
        "category": "20"
      },
      {
        "rank": 10,
        "title": "I Bend but I Don't Break",
        "video_id": "f-v4Zqph7qw",
        "url": "https://www.youtube.com/watch?v=f-v4Zqph7qw",
        "channel": "Broken Trails - Topic",
        "views": 13837,
        "likes": 355,
        "comments": 2,
        "published": "2026-07-14T10:04:55Z",
        "category": "10"
      },
      {
        "rank": 11,
        "title": "Full Other Mommy trailer recorded! 😳😱 #horror #trailer #fyp #other #mommy",
        "video_id": "T6OjtPtqe0o",
        "url": "https://www.youtube.com/watch?v=T6OjtPtqe0o",
        "channel": "BG.Edits2",
        "views": 6739,
        "likes": 78,
        "comments": 23,
        "published": "2026-07-20T06:52:43Z",
        "category": "17"
      },
      {
        "rank": 12,
        "title": "I Played EVERY Call of Duty EVER..",
        "video_id": "cLyw2TTWtQI",
        "url": "https://www.youtube.com/watch?v=cLyw2TTWtQI",
        "channel": "Im Suda",
        "views": 183899,
        "likes": 6264,
        "comments": 619,
        "published": "2026-07-19T21:18:46Z",
        "category": "20"
      },
      {
        "rank": 13,
        "title": "Masquerade Party - Among Us Song",
        "video_id": "Kr8xlhBkj3E",
        "url": "https://www.youtube.com/watch?v=Kr8xlhBkj3E",
        "channel": "CG5",
        "views": 770955,
        "likes": 60921,
        "comments": 8900,
        "published": "2026-07-18T22:00:06Z",
        "category": "10"
      },
      {
        "rank": 14,
        "title": "AVENGERS DOOMSDAY TRAILER (2026) | Steve Rogers Return | Marvel Comics | Concept",
        "video_id": "ZUHkoS4C8RE",
        "url": "https://www.youtube.com/watch?v=ZUHkoS4C8RE",
        "channel": "TeaserCon",
        "views": 128586,
        "likes": 1684,
        "comments": 86,
        "published": "2026-07-19T12:59:42Z",
        "category": "1"
      },
      {
        "rank": 15,
        "title": "ROBLOX +1 SPEED KEYBOARD ESCAPE 😱😱😱😱😱😱😲😮😮😮😳😳😳",
        "video_id": "I12L26L6-Mo",
        "url": "https://www.youtube.com/watch?v=I12L26L6-Mo",
        "channel": "Flamingo",
        "views": 682331,
        "likes": 38794,
        "comments": 4506,
        "published": "2026-07-19T17:33:58Z",
        "category": "20"
      }
    ],
    "JP_trending": [
      {
        "rank": 1,
        "title": "M!LK - しおざきわんだーらんど (塩﨑太智) (Dance Practice Movie)",
        "video_id": "lYWFDKop744",
        "url": "https://www.youtube.com/watch?v=lYWFDKop744",
        "channel": "M!LK",
        "views": 404004,
        "likes": 47503,
        "comments": 4657,
        "published": "2026-07-20T09:00:29Z",
        "category": "10"
      },
      {
        "rank": 2,
        "title": "初日に見つかる想定をしていないであろうお宝を発見してしまうk4sen【VCR RUST】",
        "video_id": "BuRqorIKPv4",
        "url": "https://www.youtube.com/watch?v=BuRqorIKPv4",
        "channel": "k4sen / かせん",
        "views": 269926,
        "likes": 6089,
        "comments": 396,
        "published": "2026-07-20T08:00:14Z",
        "category": "20"
      },
      {
        "rank": 3,
        "title": "STARGLOW / Drivin' My Life -Music Video-",
        "video_id": "zbSQaKFjyXI",
        "url": "https://www.youtube.com/watch?v=zbSQaKFjyXI",
        "channel": "STARGLOW Official",
        "views": 128391,
        "likes": 17412,
        "comments": 2109,
        "published": "2026-07-20T11:00:06Z",
        "category": "10"
      },
      {
        "rank": 4,
        "title": "W杯優勝スペインBT&STが来るんですか配信【eFootballアプリ2026/イーフト】",
        "video_id": "dXtPX9J9Ubk",
        "url": "https://www.youtube.com/watch?v=dXtPX9J9Ubk",
        "channel": "シュート。",
        "views": 178717,
        "likes": 791,
        "comments": 41,
        "published": "2026-07-20T13:07:13Z",
        "category": "20"
      },
      {
        "rank": 5,
        "title": "ジュニア【カリスマックス(Snow Man)】STAR to FESTIVAL 2026 より",
        "video_id": "stbJRUi__s0",
        "url": "https://www.youtube.com/watch?v=stbJRUi__s0",
        "channel": "ジュニアCHANNEL",
        "views": 81106,
        "likes": 9781,
        "comments": 1948,
        "published": "2026-07-20T11:00:01Z",
        "category": "24"
      },
      {
        "rank": 6,
        "title": "『詐欺グループの管理者』として明るく楽しい職場を作るゲーム【詐欺センターシミュレーター】",
        "video_id": "FO0IHwvffVo",
        "url": "https://www.youtube.com/watch?v=FO0IHwvffVo",
        "channel": "牛沢",
        "views": 243096,
        "likes": 9969,
        "comments": 704,
        "published": "2026-07-20T08:00:00Z",
        "category": "20"
      },
      {
        "rank": 7,
        "title": "BTS (방탄소년단) ‘NORMAL’ Official MV",
        "video_id": "GEk4jHwfFTA",
        "url": "https://www.youtube.com/watch?v=GEk4jHwfFTA",
        "channel": "HYBE LABELS",
        "views": 5550902,
        "likes": 968990,
        "comments": 50193,
        "published": "2026-07-19T04:00:02Z",
        "category": "10"
      },
      {
        "rank": 8,
        "title": "【#にじ甲2026】ギラギラホスト高校、1年目夏の甲子園【不破湊/にじさんじ】",
        "video_id": "q1mgn3Dq2ZI",
        "url": "https://www.youtube.com/watch?v=q1mgn3Dq2ZI",
        "channel": "不破 湊 / Fuwa Minato【にじさんじ】",
        "views": 450198,
        "likes": 6631,
        "comments": 89,
        "published": "2026-07-20T11:19:30Z",
        "category": "20"
      },
      {
        "rank": 9,
        "title": "『No More Cry』 from 超特急 BULLET TRAIN ARENA TOUR 2025「EVE」",
        "video_id": "kJvXzQO3iD8",
        "url": "https://www.youtube.com/watch?v=kJvXzQO3iD8",
        "channel": "超特急",
        "views": 62186,
        "likes": 8523,
        "comments": 606,
        "published": "2026-07-20T05:00:18Z",
        "category": "24"
      },
      {
        "rank": 10,
        "title": "AlphaAzur率いる「ア家族」のママにされ、一家を支えることになるSHAKA【VCR RUST】",
        "video_id": "c2XgE_hRwjI",
        "url": "https://www.youtube.com/watch?v=c2XgE_hRwjI",
        "channel": "SHAKAch",
        "views": 176087,
        "likes": 2622,
        "comments": 83,
        "published": "2026-07-20T05:00:02Z",
        "category": "20"
      },
      {
        "rank": 11,
        "title": "乃木坂46『命の色』MUSIC VIDEO",
        "video_id": "xpruiYFMF_g",
        "url": "https://www.youtube.com/watch?v=xpruiYFMF_g",
        "channel": "乃木坂46 OFFICIAL YouTube CHANNEL",
        "views": 210288,
        "likes": 12766,
        "comments": 1455,
        "published": "2026-07-19T10:00:36Z",
        "category": "10"
      },
      {
        "rank": 12,
        "title": "#007 『ドラゴンクエストスマッシュグロウ』の新情報を「マル」がお届け！「スマグロ マル秘 レポート」",
        "video_id": "jE3IpqDEAMY",
        "url": "https://www.youtube.com/watch?v=jE3IpqDEAMY",
        "channel": "ドラゴンクエストスマッシュグロウ公式",
        "views": 124188,
        "likes": 852,
        "comments": 298,
        "published": "2026-07-20T03:00:39Z",
        "category": "20"
      },
      {
        "rank": 13,
        "title": "U-KNOW 유노윤호 'Time's Tickin'' MV",
        "video_id": "2CsQyB-Psys",
        "url": "https://www.youtube.com/watch?v=2CsQyB-Psys",
        "channel": "SMTOWN",
        "views": 75746,
        "likes": 18586,
        "comments": 380,
        "published": "2026-07-20T09:00:01Z",
        "category": "10"
      },
      {
        "rank": 14,
        "title": "【リズム天国ミラクルスターズ】4人協力でバレー大会優勝を狙ったら熱すぎた！！【激闘】",
        "video_id": "OxPrG4XiQYk",
        "url": "https://www.youtube.com/watch?v=OxPrG4XiQYk",
        "channel": "ドズル社",
        "views": 124445,
        "likes": 5893,
        "comments": 246,
        "published": "2026-07-20T09:15:06Z",
        "category": "20"
      },
      {
        "rank": 15,
        "title": "SixTONES – マイオンリー",
        "video_id": "3lOsboT-IWU",
        "url": "https://www.youtube.com/watch?v=3lOsboT-IWU",
        "channel": "SixTONES",
        "views": 6725190,
        "likes": 69342,
        "comments": 7233,
        "published": "2026-07-17T10:00:06Z",
        "category": "10"
      }
    ],
    "KR_search": [
      {
        "rank": 1,
        "title": "아니;; 언제는 OO팬츠가 유행이라며💦 확! 달라진! 2026 여름 유행 흐름‼️",
        "video_id": "tkIARQV9TWo",
        "url": "https://www.youtube.com/watch?v=tkIARQV9TWo",
        "channel": "AliceFunk 앨리스펑크",
        "published": "2026-07-14T11:09:07Z",
        "views": 120636,
        "likes": 1348,
        "comments": 98
      },
      {
        "rank": 2,
        "title": "👀주우재가 보는 2026 하반기 패션 트렌드 그리고 주우재 최애 바지 핏은?",
        "video_id": "JfIqy2zouvo",
        "url": "https://www.youtube.com/watch?v=JfIqy2zouvo",
        "channel": "오늘의 주우재",
        "published": "2026-07-14T10:00:12Z",
        "views": 98787,
        "likes": 1177,
        "comments": 138
      },
      {
        "rank": 3,
        "title": "Dance Trend 2026 | Let Me Drive TikTok Funk #trending #viral #dance #edit #tiktok #shorts",
        "video_id": "apO4Qn6M3gE",
        "url": "https://www.youtube.com/watch?v=apO4Qn6M3gE",
        "channel": "Dance Editz",
        "published": "2026-07-19T09:15:08Z",
        "views": 154616,
        "likes": 0,
        "comments": 7
      },
      {
        "rank": 4,
        "title": "리센느, 안정적인 1위!! #리센느 #메이 #제나",
        "video_id": "ILybzjfxm2w",
        "url": "https://www.youtube.com/watch?v=ILybzjfxm2w",
        "channel": "케이팝 트렌드 KPOP Trend",
        "published": "2026-07-15T15:25:27Z",
        "views": 156530,
        "likes": 1235,
        "comments": 182
      },
      {
        "rank": 5,
        "title": "리센느, 편안한 1위!! #리센느 #원이 #미나미",
        "video_id": "Pz0eZ2Km8IA",
        "url": "https://www.youtube.com/watch?v=Pz0eZ2Km8IA",
        "channel": "케이팝 트렌드 KPOP Trend",
        "published": "2026-07-13T15:26:20Z",
        "views": 158091,
        "likes": 1243,
        "comments": 187
      },
      {
        "rank": 6,
        "title": "요즘 난리라는 &#39;힙렛&#39; 유행",
        "video_id": "VrraaftUpHQ",
        "url": "https://www.youtube.com/watch?v=VrraaftUpHQ",
        "channel": "건강행복지킴이",
        "published": "2026-07-14T08:15:06Z",
        "views": 1638904,
        "likes": 23742,
        "comments": 1267
      },
      {
        "rank": 7,
        "title": "요즘 유행하는 욕실 환풍기 진짜 쓸만할까? 전기세, 냄새, 제습 전부 테스트 해봤습니다",
        "video_id": "PwGzuBgIS9M",
        "url": "https://www.youtube.com/watch?v=PwGzuBgIS9M",
        "channel": "ITSub잇섭",
        "published": "2026-07-16T11:15:14Z",
        "views": 338494,
        "likes": 3416,
        "comments": 600
      },
      {
        "rank": 8,
        "title": "cr.迈迈 요즘 틱톡에서 유행하는 블러셔 올바르게 바르는 법 #makeuptutorial #makeup",
        "video_id": "-1sQiK_piug",
        "url": "https://www.youtube.com/watch?v=-1sQiK_piug",
        "channel": "남진 Douyin Makeup",
        "published": "2026-07-14T16:55:38Z",
        "views": 404762,
        "likes": 5206,
        "comments": 48
      },
      {
        "rank": 9,
        "title": "요즘 유행하는 파마 스타일 #각종유머 #시니어 #중년 #유머 #드라마 #shortvideo #웃긴영상 #funny #파마 #미용실",
        "video_id": "RDvqOwlMEwA",
        "url": "https://www.youtube.com/watch?v=RDvqOwlMEwA",
        "channel": "중년나이트",
        "published": "2026-07-15T01:08:48Z",
        "views": 373347,
        "likes": 5832,
        "comments": 17
      },
      {
        "rank": 10,
        "title": "요즘 유행 챌린지 미러전?! 더 잘 추는 사람은 누구? 반응 레전드 ㄷㄷ",
        "video_id": "lpjXBln1CZY",
        "url": "https://www.youtube.com/watch?v=lpjXBln1CZY",
        "channel": "수니그룹 댄스 [SOONIGROUP DANCE]",
        "published": "2026-07-18T13:51:13Z",
        "views": 358760,
        "likes": 1425,
        "comments": 130
      },
      {
        "rank": 11,
        "title": "tiktok Viral Trend | buena vida mala fama trend #tiktok #trending #buenavidamalafama#shorts #dance",
        "video_id": "GxlkpsC1FLE",
        "url": "https://www.youtube.com/watch?v=GxlkpsC1FLE",
        "channel": "tikvibez_9M",
        "published": "2026-07-14T17:47:02Z",
        "views": 8905204,
        "likes": 48493,
        "comments": 179
      },
      {
        "rank": 12,
        "title": "TikTok Viral Trend | Worry (ultra slowed) #tiktok #trending #editlyrics #lyrics #dance #viralvideo",
        "video_id": "h5hHb8fbjcU",
        "url": "https://www.youtube.com/watch?v=h5hHb8fbjcU",
        "channel": "Thunderxx Editz",
        "published": "2026-07-16T10:15:34Z",
        "views": 3262418,
        "likes": 45364,
        "comments": 2441
      },
      {
        "rank": 13,
        "title": "New Viral Tiktok Trend #tiktok #music #dance #duet #trending #usashorts #usa #viralshorts #challenge",
        "video_id": "hUYjX0AUKiM",
        "url": "https://www.youtube.com/watch?v=hUYjX0AUKiM",
        "channel": "Warzonic ",
        "published": "2026-07-15T17:26:17Z",
        "views": 3280179,
        "likes": 0,
        "comments": 590
      },
      {
        "rank": 14,
        "title": "New viral trend #tiktok #music #dance #duet #usa #usashorts #challenge #trending #viralshorts #viral",
        "video_id": "G4GBxYib-xY",
        "url": "https://www.youtube.com/watch?v=G4GBxYib-xY",
        "channel": "Rankzer",
        "published": "2026-07-14T00:25:05Z",
        "views": 2261688,
        "likes": 0,
        "comments": 1626
      },
      {
        "rank": 15,
        "title": "TikTok Viral Trend | worry (slowed) #tiktok #trending #edit #trend #dance #lyrics #viralvideo",
        "video_id": "FCueMjo-8zo",
        "url": "https://www.youtube.com/watch?v=FCueMjo-8zo",
        "channel": "beatlyGOJO",
        "published": "2026-07-17T10:00:14Z",
        "views": 1584387,
        "likes": 26100,
        "comments": 1574
      },
      {
        "rank": 16,
        "title": "안 입는 오래된 니트의 대변신! 3분 만에 명품 모자 만들기!",
        "video_id": "RjmPRHpeRjs",
        "url": "https://www.youtube.com/watch?v=RjmPRHpeRjs",
        "channel": "ChoiRakuLife",
        "published": "2026-07-16T11:00:33Z",
        "views": 1181490,
        "likes": 22434,
        "comments": 61
      },
      {
        "rank": 17,
        "title": "알아두면 평생 쓰는 마법의 바느질&amp;수선 꿀팁 7가지!",
        "video_id": "7w40T6PR7ME",
        "url": "https://www.youtube.com/watch?v=7w40T6PR7ME",
        "channel": "ChoiRakuLife",
        "published": "2026-07-15T11:00:30Z",
        "views": 452531,
        "likes": 7536,
        "comments": 23
      },
      {
        "rank": 18,
        "title": "목이 너무 높은 니트? 집에서 5분 만에 예쁜 라운드넥으로 리폼하기!",
        "video_id": "x0WSaBt95no",
        "url": "https://www.youtube.com/watch?v=x0WSaBt95no",
        "channel": "ChoiRakuLife",
        "published": "2026-07-18T11:00:35Z",
        "views": 487157,
        "likes": 11875,
        "comments": 54
      },
      {
        "rank": 19,
        "title": "안 입는 헌 옷으로 돈 한 푼 안 쓰고 예쁜 꽃 쿠션 만들기!",
        "video_id": "FK84WAWXaMc",
        "url": "https://www.youtube.com/watch?v=FK84WAWXaMc",
        "channel": "ChoiRakuLife",
        "published": "2026-07-17T11:00:21Z",
        "views": 292363,
        "likes": 4323,
        "comments": 16
      },
      {
        "rank": 20,
        "title": "알아두면 평생 써먹는 역대급 신기한 바느질 기술 8가지!",
        "video_id": "oi5o4g7WMFA",
        "url": "https://www.youtube.com/watch?v=oi5o4g7WMFA",
        "channel": "ChoiRakuLife",
        "published": "2026-07-13T11:00:27Z",
        "views": 204363,
        "likes": 3660,
        "comments": 20
      }
    ],
    "US_search": [
      {
        "rank": 1,
        "title": "Last Option🥳💥 #ismail0102 #comedy #funnyvideos #trending #funny #viral #viralvideo #support",
        "video_id": "d0I145ZNWzQ",
        "url": "https://www.youtube.com/watch?v=d0I145ZNWzQ",
        "channel": "ismail0102",
        "published": "2026-07-16T14:31:04Z",
        "views": 5597006,
        "likes": 128755,
        "comments": 683
      },
      {
        "rank": 2,
        "title": "COUPLE IN POWER—Nosa Rex | Sarian Martin #trending #latestnigerianmovies #nollywoodmovies #viral",
        "video_id": "ON8doAoeCtY",
        "url": "https://www.youtube.com/watch?v=ON8doAoeCtY",
        "channel": "NOSAREXFAMTV",
        "published": "2026-07-13T15:59:26Z",
        "views": 2375904,
        "likes": 33136,
        "comments": 2777
      },
      {
        "rank": 3,
        "title": "A cute, chubby 4-year-old Indian toddler wearing .... #ai #trending #viral #shorts #mrbeast #trend",
        "video_id": "u7ZAFaXm_2k",
        "url": "https://www.youtube.com/watch?v=u7ZAFaXm_2k",
        "channel": "Punjab Toons Hub",
        "published": "2026-07-15T03:10:22Z",
        "views": 4433645,
        "likes": 18050,
        "comments": 10
      },
      {
        "rank": 4,
        "title": "Brithday Karab 🤣🤣#shorts #comedy #funny #trending #viral #youtube #video",
        "video_id": "waO9SBBL6JI",
        "url": "https://www.youtube.com/watch?v=waO9SBBL6JI",
        "channel": "Bittu Chouhan",
        "published": "2026-07-14T02:30:22Z",
        "views": 3513704,
        "likes": 35301,
        "comments": 10
      },
      {
        "rank": 5,
        "title": "रोटी नहीं बनी 😱 #trending #cutebaby #viral #shortvideo #funny",
        "video_id": "Z4n92VYd-Lw",
        "url": "https://www.youtube.com/watch?v=Z4n92VYd-Lw",
        "channel": "Ajay Sonia Vlogs",
        "published": "2026-07-13T13:00:00Z",
        "views": 3364526,
        "likes": 16701,
        "comments": 19
      },
      {
        "rank": 6,
        "title": "tiktok Viral Trend | buena vida mala fama trend #tiktok #trending #buenavidamalafama#shorts #dance",
        "video_id": "GxlkpsC1FLE",
        "url": "https://www.youtube.com/watch?v=GxlkpsC1FLE",
        "channel": "tikvibez_9M",
        "published": "2026-07-14T17:47:02Z",
        "views": 8905204,
        "likes": 48493,
        "comments": 179
      },
      {
        "rank": 7,
        "title": "TikTok Viral Trend | Worry (ultra slowed) #tiktok #trending #editlyrics #lyrics #dance #viralvideo",
        "video_id": "h5hHb8fbjcU",
        "url": "https://www.youtube.com/watch?v=h5hHb8fbjcU",
        "channel": "Thunderxx Editz",
        "published": "2026-07-16T10:15:34Z",
        "views": 3262418,
        "likes": 45364,
        "comments": 2441
      },
      {
        "rank": 8,
        "title": "New viral trend #tiktok #music #dance #duet #usa #usashorts #challenge #trending #viralshorts #viral",
        "video_id": "G4GBxYib-xY",
        "url": "https://www.youtube.com/watch?v=G4GBxYib-xY",
        "channel": "Rankzer",
        "published": "2026-07-14T00:25:05Z",
        "views": 2261688,
        "likes": 0,
        "comments": 1626
      },
      {
        "rank": 9,
        "title": "TikTok Viral Trend | Buena Vida Mala Fama #tiktok #trending #edit #trend #dance #lyrics #viralvideo",
        "video_id": "E5eQ1YDI0pY",
        "url": "https://www.youtube.com/watch?v=E5eQ1YDI0pY",
        "channel": "beatlyGOJO",
        "published": "2026-07-17T05:00:20Z",
        "views": 1980091,
        "likes": 23641,
        "comments": 190
      },
      {
        "rank": 10,
        "title": "TikTok Viral Trend | worry (slowed) #tiktok #trending #edit #trend #dance #lyrics #viralvideo",
        "video_id": "FCueMjo-8zo",
        "url": "https://www.youtube.com/watch?v=FCueMjo-8zo",
        "channel": "beatlyGOJO",
        "published": "2026-07-17T10:00:14Z",
        "views": 1584387,
        "likes": 26108,
        "comments": 1574
      },
      {
        "rank": 11,
        "title": "Best Water Hose Leak Repair Hack | DIY Plumbing Tips #shorts",
        "video_id": "Q080KLElTf4",
        "url": "https://www.youtube.com/watch?v=Q080KLElTf4",
        "channel": "AB electrician⚡",
        "published": "2026-07-16T03:31:10Z",
        "views": 3346605,
        "likes": 22379,
        "comments": 112
      },
      {
        "rank": 12,
        "title": "Useful tips 02 #cookingtips #diy #homehacks #ideas #kitchenhacks #lifehacks #lifetips #tips #shorts",
        "video_id": "y5yJg4wtOHk",
        "url": "https://www.youtube.com/watch?v=y5yJg4wtOHk",
        "channel": "Adam Fan 888",
        "published": "2026-07-15T16:48:46Z",
        "views": 1675056,
        "likes": 31225,
        "comments": 150
      },
      {
        "rank": 13,
        "title": "DIY Fly Trap Hack! 🪰 #shorts #lifehacks #tips #homemade #hacks",
        "video_id": "iSHQhbqZl-E",
        "url": "https://www.youtube.com/watch?v=iSHQhbqZl-E",
        "channel": "Safak Novruz",
        "published": "2026-07-13T11:06:18Z",
        "views": 965010,
        "likes": 3614,
        "comments": 57
      },
      {
        "rank": 14,
        "title": "How to Survive a Heatwave inside a Blanket 🧊 #summer #heatwave  #tips",
        "video_id": "pgm7pY4r8RU",
        "url": "https://www.youtube.com/watch?v=pgm7pY4r8RU",
        "channel": "Priborker",
        "published": "2026-07-18T15:05:23Z",
        "views": 894549,
        "likes": 12398,
        "comments": 127
      },
      {
        "rank": 15,
        "title": "12 Amazing Home Hacks That Will Blow Your Mind! #shorts #lifehacks #diy",
        "video_id": "bkGCf6Gtg-Q",
        "url": "https://www.youtube.com/watch?v=bkGCf6Gtg-Q",
        "channel": "DD Films",
        "published": "2026-07-17T14:00:15Z",
        "views": 711158,
        "likes": 18358,
        "comments": 17
      },
      {
        "rank": 16,
        "title": "Chaku Se Tamatar Nhi Kat Raha Hai 😖 | #minivlog #viral #cooking #dailyvlog #recipe #food #shorts",
        "video_id": "r_kv4EfBAt0",
        "url": "https://www.youtube.com/watch?v=r_kv4EfBAt0",
        "channel": "Lado Vlogs",
        "published": "2026-07-13T11:30:30Z",
        "views": 31043679,
        "likes": 334766,
        "comments": 971
      },
      {
        "rank": 17,
        "title": "Sanya Ne Banwayi Viral Lays Chaat Recipe!🤤#shorts #layschaat #familydrama #foodvlog #recipe",
        "video_id": "iUFqzSTtrS4",
        "url": "https://www.youtube.com/watch?v=iUFqzSTtrS4",
        "channel": "KK Family Drama",
        "published": "2026-07-14T13:09:45Z",
        "views": 6788678,
        "likes": 130346,
        "comments": 582
      },
      {
        "rank": 18,
        "title": "నీ భర్తకు నువ్వే వడ్డించాలి.. నా భర్తకి నేను వడ్డిస్తాను #shorts #viral #trending #youtubeshorts",
        "video_id": "AAxStPZbM9I",
        "url": "https://www.youtube.com/watch?v=AAxStPZbM9I",
        "channel": "Durgadevi Arigala",
        "published": "2026-07-13T05:30:33Z",
        "views": 4668557,
        "likes": 37627,
        "comments": 69
      },
      {
        "rank": 19,
        "title": "పండు ముసలివారినుంచి చిన్నపిల్లలా😋😋👌,#sweetykichen ,#recipe ,#food ,#yt ,#short ,#viral ,#foodie .",
        "video_id": "_1e-xSr5__E",
        "url": "https://www.youtube.com/watch?v=_1e-xSr5__E",
        "channel": "Sweetykitchen ",
        "published": "2026-07-14T06:30:04Z",
        "views": 2852662,
        "likes": 45949,
        "comments": 196
      },
      {
        "rank": 20,
        "title": "**Pizza🍕ka partition kon karta hai🤦‍♀️**#shorts #trending #cooking #viral #recipe #ytshorts #easy",
        "video_id": "Dneb7f7Id_o",
        "url": "https://www.youtube.com/watch?v=Dneb7f7Id_o",
        "channel": "Ekta@thisside🌼",
        "published": "2026-07-14T07:36:45Z",
        "views": 2405656,
        "likes": 50564,
        "comments": 127
      }
    ],
    "JP_search": [
      {
        "rank": 1,
        "title": "話題のモナキをDIMEが撮り下ろしインタビュー！2026年上半期トレンドを深掘り",
        "video_id": "sV25TNT3C3E",
        "url": "https://www.youtube.com/watch?v=sV25TNT3C3E",
        "channel": "DIME",
        "published": "2026-07-14T10:06:40Z",
        "views": 105383,
        "likes": 129,
        "comments": 0
      },
      {
        "rank": 2,
        "title": "India Joins Exercise Pitch Black 2026 With Rafale! #defence #india #shorts",
        "video_id": "DdXM8zSrMCE",
        "url": "https://www.youtube.com/watch?v=DdXM8zSrMCE",
        "channel": "DefNexus",
        "published": "2026-07-17T16:00:16Z",
        "views": 2671,
        "likes": 194,
        "comments": 6
      },
      {
        "rank": 3,
        "title": "His Reaction To Fake Sneezes Is The Sweetest Thing Ever! 🥺😂 momlife heart full ❣️ #momlifeheartfull",
        "video_id": "ExoHHfMGdeA",
        "url": "https://www.youtube.com/watch?v=ExoHHfMGdeA",
        "channel": "Momlife Heart full",
        "published": "2026-07-18T17:00:31Z",
        "views": 2573,
        "likes": 47,
        "comments": 1
      },
      {
        "rank": 4,
        "title": "Autam Goat Farm 2026 Goat Collection Ph :  7439235173#goat#Farm#Viral#Trending#2026",
        "video_id": "QXacWLghidY",
        "url": "https://www.youtube.com/watch?v=QXacWLghidY",
        "channel": "Animals lover Imran",
        "published": "2026-07-14T09:53:57Z",
        "views": 1726,
        "likes": 0,
        "comments": 3
      },
      {
        "rank": 5,
        "title": "2000 #puppy #goldenretreiver #funny #cute #shortsfeed #plsgoviral #trend #trending #like",
        "video_id": "sG3dniklRsI",
        "url": "https://www.youtube.com/watch?v=sG3dniklRsI",
        "channel": "Milo The Borador",
        "published": "2026-07-17T22:54:28Z",
        "views": 816,
        "likes": 6,
        "comments": 1
      },
      {
        "rank": 6,
        "title": "Viral Trend In America VS Middle East",
        "video_id": "drsq3xij-vM",
        "url": "https://www.youtube.com/watch?v=drsq3xij-vM",
        "channel": "Blatant Reviews",
        "published": "2026-07-14T22:07:18Z",
        "views": 990914,
        "likes": 52397,
        "comments": 146
      },
      {
        "rank": 7,
        "title": "Rap Songs That Gen Z RUINED😭🎵#tiktok #trending #shorts",
        "video_id": "hL9yXK6rrRg",
        "url": "https://www.youtube.com/watch?v=hL9yXK6rrRg",
        "channel": "TheRapLab",
        "published": "2026-07-16T22:00:00Z",
        "views": 448845,
        "likes": 9682,
        "comments": 131
      },
      {
        "rank": 8,
        "title": "xQc Reacts to His Most Viral Clips and Tiktoks Ever!",
        "video_id": "D314z2jioD8",
        "url": "https://www.youtube.com/watch?v=D314z2jioD8",
        "channel": "ImStillxQc",
        "published": "2026-07-19T16:30:39Z",
        "views": 16321,
        "likes": 418,
        "comments": 22
      },
      {
        "rank": 9,
        "title": "2026年に流行ったTikTokメドレー#TikTokメドレー #TikTok人気曲#最新TikTokメドレー💟",
        "video_id": "xa4lDOlcW80",
        "url": "https://www.youtube.com/watch?v=xa4lDOlcW80",
        "channel": "最新TIKTOKメドレー",
        "published": "2026-07-13T05:00:22Z",
        "views": 12500,
        "likes": 56,
        "comments": 2
      },
      {
        "rank": 10,
        "title": "[最新TikTokメドレー]🌴",
        "video_id": "y4RiEmu_eAY",
        "url": "https://www.youtube.com/watch?v=y4RiEmu_eAY",
        "channel": "TikTokメドレー Daily",
        "published": "2026-07-18T05:00:30Z",
        "views": 8279,
        "likes": 32,
        "comments": 0
      },
      {
        "rank": 11,
        "title": "貝殻アイテム🥰 #shorts #ハンドメイド #100均 #100均diy #ライフハック",
        "video_id": "ZMBfgpDFsps",
        "url": "https://www.youtube.com/watch?v=ZMBfgpDFsps",
        "channel": "あんの遊びチャンネル",
        "published": "2026-07-14T08:55:16Z",
        "views": 102427,
        "likes": 2286,
        "comments": 24
      },
      {
        "rank": 12,
        "title": "捨てるの待って！針金ハンガーが神収納グッズに大変身【5選】✨",
        "video_id": "ehChep6R2d4",
        "url": "https://www.youtube.com/watch?v=ehChep6R2d4",
        "channel": "ちょい得ライフハック",
        "published": "2026-07-13T07:59:34Z",
        "views": 23397,
        "likes": 178,
        "comments": 1
      },
      {
        "rank": 13,
        "title": "【ダイソー再販】550円ラックが神変身！工具なしで作れるハンガーラック",
        "video_id": "t83f2hScT1I",
        "url": "https://www.youtube.com/watch?v=t83f2hScT1I",
        "channel": "役立つヒント",
        "published": "2026-07-17T09:44:43Z",
        "views": 20470,
        "likes": 120,
        "comments": 1
      },
      {
        "rank": 14,
        "title": "【100均だけ】神収納棚が550円から作れる！散らかった部屋が一瞬でスッキリ✨",
        "video_id": "j4XtGS81mWU",
        "url": "https://www.youtube.com/watch?v=j4XtGS81mWU",
        "channel": "Yakashi",
        "published": "2026-07-13T07:30:04Z",
        "views": 15895,
        "likes": 148,
        "comments": 0
      },
      {
        "rank": 15,
        "title": "ダイソーだけで神収納完成✨ 散らかり問題が一気に解決😍",
        "video_id": "znVZcPFa9y0",
        "url": "https://www.youtube.com/watch?v=znVZcPFa9y0",
        "channel": "Choi-waza Kurashi",
        "published": "2026-07-16T09:39:09Z",
        "views": 16994,
        "likes": 191,
        "comments": 3
      },
      {
        "rank": 16,
        "title": "僕の料理を完全否定したアンチのレシピ作ってみた",
        "video_id": "HZ_vcGO-5pY",
        "url": "https://www.youtube.com/watch?v=HZ_vcGO-5pY",
        "channel": "料理研究家リュウジのバズレシピ",
        "published": "2026-07-17T10:00:04Z",
        "views": 512752,
        "likes": 8605,
        "comments": 1713
      },
      {
        "rank": 17,
        "title": "二度とパスタに戻れなくなる冷やしカルボナーラ",
        "video_id": "t8DFxWJuPiM",
        "url": "https://www.youtube.com/watch?v=t8DFxWJuPiM",
        "channel": "料理研究家リュウジのバズレシピ",
        "published": "2026-07-14T10:24:46Z",
        "views": 505537,
        "likes": 11131,
        "comments": 599
      },
      {
        "rank": 18,
        "title": "ローソンがこれだけはまじで自信があるって持ってきた、このニンニクまぜそば。まじでウマいのかガチジャッジします #PR #ローソン",
        "video_id": "-0AME96oPCg",
        "url": "https://www.youtube.com/watch?v=-0AME96oPCg",
        "channel": "料理研究家リュウジのバズレシピ",
        "published": "2026-07-16T08:00:03Z",
        "views": 578937,
        "likes": 5363,
        "comments": 101
      },
      {
        "rank": 19,
        "title": "中本、あのさぁ…",
        "video_id": "33Mx_XsVW4g",
        "url": "https://www.youtube.com/watch?v=33Mx_XsVW4g",
        "channel": "料理研究家リュウジのバズレシピ",
        "published": "2026-07-18T10:15:30Z",
        "views": 284142,
        "likes": 2799,
        "comments": 612
      },
      {
        "rank": 20,
        "title": "ソーセージをバカほど入れたワンパンで作るペペロンチーノが世界で一番ウマいペペロンチーノです #PR #燻製屋",
        "video_id": "APh32zF-FWM",
        "url": "https://www.youtube.com/watch?v=APh32zF-FWM",
        "channel": "料理研究家リュウジのバズレシピ",
        "published": "2026-07-13T08:00:07Z",
        "views": 561990,
        "likes": 9870,
        "comments": 126
      }
    ]
  },
  "collected_at": "2026-07-20T15:57:33.308957+00:00"
}